shipping/__init__.py
shipping/__main__.py
shipping/cli/__init__.py
shipping/cli/base.py
shipping/cli/check.py
shipping/cli/config.py
shipping/cli/deploy.py
shipping/cli/provision.py
shipping/commands.py
shipping/configs/__init__.py
shipping/configs/base_config.py
shipping/deploy/__init__.py
shipping/deploy/conda.py
shipping/environment.py
shipping/log.py
shipping/package.py
shipping-0.2.2.dist-info/entry_points.txt
shipping-0.2.2.dist-info/LICENSE
shipping-0.2.2.dist-info/WHEEL
shipping-0.2.2.dist-info/METADATA
shipping-0.2.2.dist-info/RECORD
