Metadata-Version: 2.1
Name: shipping
Version: 0.2.2
Summary: Cli utility for deploying packages
Home-page: https://github.com/ClinicalGenomics/shipping/
License: MIT
Keywords: Deployment,Virtual Environments,Containers,Conda,Packaging
Author: Måns Magnusson
Author-email: mans.magnusson@scilifelab.se
Maintainer: Måns Magnusson
Maintainer-email: mans.magnusson@scilifelab.se
Requires-Python: >=3.7,<4.0
Classifier: License :: OSI Approved :: MIT License
Classifier: Programming Language :: Python :: 3
Classifier: Programming Language :: Python :: 3.7
Classifier: Programming Language :: Python :: 3.8
Classifier: Programming Language :: Python :: 3.9
Requires-Dist: click (>=7.1.2,<8.0.0)
Requires-Dist: coloredlogs (>=14.0,<15.0)
Requires-Dist: importlib-metadata (>=1.0,<2.0); python_version < "3.8"
Requires-Dist: pydantic (>=1.6.1,<2.0.0)
Requires-Dist: pytz (>=2020.1,<2021.0)
Requires-Dist: pyyaml (>=5.3.1,<6.0.0)
Project-URL: Repository, https://github.com/ClinicalGenomics/shipping/
